slackblocks/__init__.py
slackblocks/attachments.py
slackblocks/blocks.py
slackblocks/elements.py
slackblocks/errors.py
slackblocks/messages.py
slackblocks/modals.py
slackblocks/objects.py
slackblocks/rich_text/__init__.py
slackblocks/rich_text/elements.py
slackblocks/rich_text/objects.py
slackblocks/utils.py
slackblocks/views.py
slackblocks-1.2.3.dist-info/LICENSE
slackblocks-1.2.3.dist-info/WHEEL
slackblocks-1.2.3.dist-info/LICENSE.BSD-3-Clause
slackblocks-1.2.3.dist-info/METADATA
slackblocks-1.2.3.dist-info/RECORD
