Metadata-Version: 2.1
Name: slackblocks
Version: 1.2.3
Summary: Python wrapper for the Slack Blocks API
Home-page: https://github.com/nicklambourne/slackblocks
License: MIT
Keywords: slackblocks,slack,messaging,message generation,slack blocks,blocks
Author: Nicholas Lambourne
Author-email: dev@ndl.im
Maintainer: Nicholas Lambourne
Maintainer-email: dev@ndl.im
Requires-Python: >=3.8.1
Classifier: License :: OSI Approved :: BSD License
Classifier: License :: OSI Approved :: MIT License
Classifier: Operating System :: OS Independent
Classifier: Programming Language :: Python :: 3
Classifier: Programming Language :: Python :: 3.9
Classifier: Programming Language :: Python :: 3.10
Classifier: Programming Language :: Python :: 3.11
Classifier: Programming Language :: Python :: 3.10
Classifier: Programming Language :: Python :: 3.11
Classifier: Programming Language :: Python :: 3.12
Classifier: Programming Language :: Python :: 3.13
Classifier: Programming Language :: Python :: 3.14
Classifier: Programming Language :: Python :: 3.8
Classifier: Programming Language :: Python :: 3.9
Classifier: Topic :: Communications :: Chat
Classifier: Typing :: Typed
Project-URL: Repository, https://github.com/nicklambourne/slackblocks
